MANIFEST.in
requirements.txt
setup.py
warmongo/__init__.py
warmongo/database.py
warmongo/exceptions.py
warmongo/model.py
warmongo/model_base.py
warmongo.egg-info/PKG-INFO
warmongo.egg-info/SOURCES.txt
warmongo.egg-info/dependency_links.txt
warmongo.egg-info/requires.txt
warmongo.egg-info/top_level.txt